LICENSE.txt
MANIFEST.in
README.md
requirements-tests.txt
setup.cfg
setup.py
pyrehol/__init__.py
pyrehol.egg-info/PKG-INFO
pyrehol.egg-info/SOURCES.txt
pyrehol.egg-info/dependency_links.txt
pyrehol.egg-info/top_level.txt