Metadata-Version: 1.1
Name: pyrehol
Version: 0.3
Summary: Python library for generating FireHOL config
Home-page: https://github.com/uber/pyrehol
Author: James Brown
Author-email: jbrown@uber.com
License: MIT (Expat)
Platform: UNKNOWN
Classifier: Programming Language :: Python
Classifier: Operating System :: OS Independent
Classifier: Topic :: Security
Classifier: Intended Audience :: System Administrators
Classifier: Development Status :: 3 - Alpha
Classifier: Programming Language :: Python :: 2.7
Classifier: License :: OSI Approved :: MIT License
